{
    "CADASTRAIS": {
        "CPF": "1110809590",
        "NOME": "MUNIQUE GOMES DE OLIVEIRA",
        "NOME_MAE": "CLEUSA ESMERIA DE OLIVEIRA",
        "NASCTO": "28\/11\/1984",
        "IDADE": "41 anos",
        "SEXO": "Feminino",
        "RG": "1304215458",
        "ORGAO_EMISSOR": "",
        "UF_EMISSAO": "",
        "TITULO_ELEITOR": "110729050566",
        "NIT": "2686310186",
        "ESCOLARIDADE": "",
        "NACIONALIDADE": "Brasileiro ",
        "CBO": "521105",
        "PROFISSAO": "VENDEDOR EM COMERCIO ATACADISTA",
        "SALARIO": " 2.000,00",
        "CLASSE_ECONOMICA": "D",
        "CONSTA_OBITO": ""
    },
    "TELEFONES_FIXO": {
        "TELEFONE": [
            {
                "NUMERO": "7135073692",
                "OPERADORA": "CLARO S.A.",
                "DATA_REFERENCIA": "",
                "TIPO_TEL": "FIXO",
                "TEM_ZAP": "",
                "NAO_PERTUBE": "não",
                "IMG": "",
                "PRIORIDADE": "alta"
            },
            {
                "NUMERO": "7130374924",
                "OPERADORA": "VIVO",
                "DATA_REFERENCIA": "",
                "TIPO_TEL": "FIXO",
                "TEM_ZAP": "",
                "NAO_PERTUBE": "não",
                "IMG": "",
                "PRIORIDADE": "media"
            },
            {
                "NUMERO": "7132326870",
                "OPERADORA": "TELEMAR\/BA",
                "DATA_REFERENCIA": "",
                "TIPO_TEL": "FIXO",
                "TEM_ZAP": "",
                "NAO_PERTUBE": "não",
                "IMG": "",
                "PRIORIDADE": "media"
            }
        ]
    },
    "TELEFONES_MOVEL": {
        "TELEFONE": [
            {
                "NUMERO": "71999561283",
                "OPERADORA": "VIVO",
                "DATA_REFERENCIA": "",
                "TIPO_TEL": "MOVEL",
                "TEM_ZAP": "",
                "NAO_PERTUBE": "não",
                "IMG": "",
                "PRIORIDADE": "alta"
            },
            {
                "NUMERO": "33988678315",
                "OPERADORA": "OI MOVEL S.A.",
                "DATA_REFERENCIA": "",
                "TIPO_TEL": "MOVEL",
                "TEM_ZAP": "",
                "NAO_PERTUBE": "não",
                "IMG": "",
                "PRIORIDADE": "alta"
            },
            {
                "NUMERO": "71982846037",
                "OPERADORA": "CLARO S.A.",
                "DATA_REFERENCIA": "",
                "TIPO_TEL": "CLARO PRE PAGO",
                "TEM_ZAP": "",
                "NAO_PERTUBE": "não",
                "IMG": "",
                "PRIORIDADE": "alta"
            },
            {
                "NUMERO": "71988894924",
                "OPERADORA": "OI MOVEL S.A.",
                "DATA_REFERENCIA": "",
                "TIPO_TEL": "PRE PAGO",
                "TEM_ZAP": "",
                "NAO_PERTUBE": "não",
                "IMG": "",
                "PRIORIDADE": "alta"
            },
            {
                "NUMERO": "71999295963",
                "OPERADORA": "VIVO",
                "DATA_REFERENCIA": "",
                "TIPO_TEL": "MOVEL",
                "TEM_ZAP": "",
                "NAO_PERTUBE": "não",
                "IMG": "",
                "PRIORIDADE": "media"
            }
        ]
    },
    "EMAILS": {
        "EMAIL": [
            "pradobentoneto@hotmail.com",
            "japersil@zipmail.com.br",
            "muniqueoliveirag@gmail.com"
        ]
    },
    "ENDERECOS": {
        "ENDERECO": [
            {
                "LOGRADOURO": "R DR GERINO DE SOUZA FILHO",
                "NUMERO": "5197",
                "COMPLEMENTO": "BL 18406",
                "BAIRRO": "CAIXA D AGUA",
                "CEP": "42711830",
                "CIDADE": "LAURO DE FREITAS",
                "ESTADO": "BA"
            },
            {
                "LOGRADOURO": "R DR GERINO DE SOUZA FILHO",
                "NUMERO": "5197",
                "COMPLEMENTO": "BL 18 AP 40",
                "BAIRRO": "RCR IPITANGA",
                "CEP": "42700210",
                "CIDADE": "LAURO DE FREITAS",
                "ESTADO": "BA"
            },
            {
                "LOGRADOURO": "R ERALDO",
                "NUMERO": "68",
                "COMPLEMENTO": "",
                "BAIRRO": "ENGENHO VELHO DA FEDERACAO",
                "CEP": "40220020",
                "CIDADE": "SALVADOR",
                "ESTADO": "BA"
            },
            {
                "LOGRADOURO": "AV DIAS",
                "NUMERO": "79",
                "COMPLEMENTO": "CB",
                "BAIRRO": "CAPELINHA",
                "CEP": "40393500",
                "CIDADE": "SALVADOR",
                "ESTADO": "BA"
            },
            {
                "LOGRADOURO": "QD 13",
                "NUMERO": "0",
                "COMPLEMENTO": "AR 6 A",
                "BAIRRO": "SOBRADINHO",
                "CEP": "73040130",
                "CIDADE": "BRASILIA",
                "ESTADO": "DF"
            },
            {
                "LOGRADOURO": "AL VERONA",
                "NUMERO": "112",
                "COMPLEMENTO": "ED CEDRO REDIDÊNCIA AP 1102",
                "BAIRRO": "PITUBA",
                "CEP": "41830465",
                "CIDADE": "SALVADOR",
                "ESTADO": "BA"
            },
            {
                "LOGRADOURO": "R TENENTE GUSTAVO DOS SANTOS",
                "NUMERO": "153",
                "COMPLEMENTO": "",
                "BAIRRO": "BOCA DO RIO",
                "CEP": "41706860",
                "CIDADE": "SALVADOR",
                "ESTADO": "BA"
            },
            {
                "LOGRADOURO": "RUA HEITOR DIAS",
                "NUMERO": "79",
                "COMPLEMENTO": "CASA FU",
                "BAIRRO": "BOCA DO RIO",
                "CEP": "41710745",
                "CIDADE": "SALVADOR",
                "ESTADO": "BA"
            }
        ]
    },
    "POSSIVEIS_PARENTES": {
        "CONTATO": [
            {
                "CPF": "47231238653",
                "NOME": "CLEUSA ESMERIA DE OLIVEIRA",
                "IDADE": "67 anos",
                "LOCAL": "CACHOEIRA DE PAJEU\/MG",
                "PARENTESCO": "MAE"
            },
            {
                "CPF": "6574691737",
                "NOME": "PEDRO HENRIQUE DE OLIVEIRA MAIA",
                "IDADE": "15 anos",
                "LOCAL": "",
                "PARENTESCO": "FILHO(A)"
            },
            {
                "CPF": "6574698740",
                "NOME": "QUEREN GOMES DE OLIVEIRA",
                "IDADE": "22 anos",
                "LOCAL": "TANGUA\/RJ",
                "PARENTESCO": "FILHO(A)"
            }
        ]
    },
    "POSSIVEIS_CONTATOS": {
        "CONTATO": {
            "NOME": "JAIME PEREIRA DA SILVA",
            "IDADE": "",
            "LOCALIDADE": "NOVA IGUACU\/RJ",
            "TP_VINCULO": "E-MAIL",
            "CPF": "33408475768"
        }
    },
    "REFERENCIA_PROFISSIONAL": {
        "EMPRESA": [
            {
                "RAZAO_SOCIAL": "NOVO MIX ATACADO DE ALIMENTOS LTDA",
                "CNPJ": "27326415000106",
                "CIDADE": "SIMOES FILHO-BA",
                "PROFISSAO": "411010",
                "DATA_ADMISSAO": "24\/01\/2024",
                "DATA_DEMISSAO": "16\/02\/2026",
                "MOTIVO_DESLIGAMENTO": "",
                "ANO_BASE": "2024"
            },
            {
                "RAZAO_SOCIAL": "BONMESS INDUSTRIA DE ALIMENTOS LTDA",
                "CNPJ": "24151661000186",
                "CIDADE": "LAURO DE FREITAS-BA",
                "PROFISSAO": "521105",
                "DATA_ADMISSAO": "22\/11\/2023",
                "DATA_DEMISSAO": "23\/01\/2026",
                "MOTIVO_DESLIGAMENTO": "",
                "ANO_BASE": "2024"
            },
            {
                "RAZAO_SOCIAL": "ARAUJO MATEUS IMPORTACAO E COMERCIO LTDA FALIDO",
                "CNPJ": "15211402000102",
                "CIDADE": "SALVADOR-BA",
                "PROFISSAO": "354210",
                "DATA_ADMISSAO": "01\/12\/2010",
                "DATA_DEMISSAO": "06\/08\/2026",
                "MOTIVO_DESLIGAMENTO": "",
                "ANO_BASE": "2023"
            }
        ]
    },
    "EMPRESAS_SOCIO": ""
}