{
    "CADASTRAIS": {
        "CPF": "7638750748",
        "NOME": "VIVIANE FONSECA TEIXEIRA",
        "NOME_MAE": "VERA LUCIA FONSECA TEIXEIRA",
        "NASCTO": "29\/06\/1976",
        "IDADE": "49 anos",
        "SEXO": "Feminino",
        "RG": "",
        "ORGAO_EMISSOR": "",
        "UF_EMISSAO": "",
        "TITULO_ELEITOR": "085644290337",
        "NIT": "19008863378",
        "ESCOLARIDADE": "SUPERIOR COMPLETO",
        "NACIONALIDADE": "",
        "CBO": "252105",
        "PROFISSAO": "ADMINISTRADOR",
        "SALARIO": " 5.678,00",
        "CLASSE_ECONOMICA": "C",
        "CONSTA_OBITO": ""
    },
    "TELEFONES_FIXO": {
        "TELEFONE": [
            {
                "NUMERO": "2226476333",
                "OPERADORA": "TELEMAR NORTE LESTE S.A.",
                "DATA_REFERENCIA": "",
                "TIPO_TEL": "FIXO",
                "TEM_ZAP": "",
                "NAO_PERTUBE": "não",
                "IMG": "",
                "PRIORIDADE": "alta"
            },
            {
                "NUMERO": "1155830592",
                "OPERADORA": "VIVO",
                "DATA_REFERENCIA": "",
                "TIPO_TEL": "FIXO",
                "TEM_ZAP": "",
                "NAO_PERTUBE": "não",
                "IMG": "",
                "PRIORIDADE": "media"
            },
            {
                "NUMERO": "2130682298",
                "OPERADORA": "CLARO S.A.",
                "DATA_REFERENCIA": "",
                "TIPO_TEL": "FIXO",
                "TEM_ZAP": "",
                "NAO_PERTUBE": "não",
                "IMG": "",
                "PRIORIDADE": "media"
            },
            {
                "NUMERO": "2226474620",
                "OPERADORA": "TELEMAR NORTE LESTE S.A.",
                "DATA_REFERENCIA": "",
                "TIPO_TEL": "FIXO",
                "TEM_ZAP": "",
                "NAO_PERTUBE": "não",
                "IMG": "",
                "PRIORIDADE": "media"
            }
        ]
    },
    "TELEFONES_MOVEL": {
        "TELEFONE": [
            {
                "NUMERO": "21998588316",
                "OPERADORA": "VIVO",
                "DATA_REFERENCIA": "",
                "TIPO_TEL": "MOVEL",
                "TEM_ZAP": "",
                "NAO_PERTUBE": "não",
                "IMG": "",
                "PRIORIDADE": "alta"
            },
            {
                "NUMERO": "22998254568",
                "OPERADORA": "VIVO",
                "DATA_REFERENCIA": "",
                "TIPO_TEL": "MOVEL",
                "TEM_ZAP": "",
                "NAO_PERTUBE": "não",
                "IMG": "",
                "PRIORIDADE": "alta"
            },
            {
                "NUMERO": "22998588316",
                "OPERADORA": "VIVO",
                "DATA_REFERENCIA": "",
                "TIPO_TEL": "PRE PAGO",
                "TEM_ZAP": "",
                "NAO_PERTUBE": "não",
                "IMG": "",
                "PRIORIDADE": "alta"
            },
            {
                "NUMERO": "22998338316",
                "OPERADORA": "VIVO",
                "DATA_REFERENCIA": "",
                "TIPO_TEL": "MOVEL",
                "TEM_ZAP": "",
                "NAO_PERTUBE": "não",
                "IMG": "",
                "PRIORIDADE": "baixa"
            },
            {
                "NUMERO": "22998371334",
                "OPERADORA": "VIVO",
                "DATA_REFERENCIA": "",
                "TIPO_TEL": "MOVEL",
                "TEM_ZAP": "",
                "NAO_PERTUBE": "não",
                "IMG": "",
                "PRIORIDADE": "baixa"
            }
        ]
    },
    "EMAILS": {
        "EMAIL": [
            "viviane.fteixeira29@gmail.com",
            "viviane_fteixeira@hotmail.com"
        ]
    },
    "ENDERECOS": {
        "ENDERECO": [
            {
                "LOGRADOURO": "R MNS JERONIMO",
                "NUMERO": "860",
                "COMPLEMENTO": "",
                "BAIRRO": "ENGENHO DE DENTRO",
                "CEP": "20730110",
                "CIDADE": "RIO DE JANEIRO",
                "ESTADO": "RJ"
            },
            {
                "LOGRADOURO": "R TEIXEIRA DE AZEVEDO",
                "NUMERO": "384",
                "COMPLEMENTO": "",
                "BAIRRO": "ABOLICAO",
                "CEP": "20755260",
                "CIDADE": "RIO DE JANEIRO",
                "ESTADO": "RJ"
            },
            {
                "LOGRADOURO": "R BUARQUE DE MACEDO",
                "NUMERO": "70",
                "COMPLEMENTO": "802",
                "BAIRRO": "FLAMENGO",
                "CEP": "22220030",
                "CIDADE": "RIO DE JANEIRO",
                "ESTADO": "RJ"
            },
            {
                "LOGRADOURO": "R APERIBE",
                "NUMERO": "219",
                "COMPLEMENTO": "",
                "BAIRRO": "TAQUARA",
                "CEP": "22720180",
                "CIDADE": "RIO DE JANEIRO",
                "ESTADO": "RJ"
            },
            {
                "LOGRADOURO": "R BUARQUE DE MACEDO",
                "NUMERO": "70802",
                "COMPLEMENTO": "",
                "BAIRRO": "FLAMENGO",
                "CEP": "22220030",
                "CIDADE": "RIO DE JANEIRO",
                "ESTADO": "RJ"
            },
            {
                "LOGRADOURO": "R BUARQUE DE MACEDO",
                "NUMERO": "802",
                "COMPLEMENTO": "",
                "BAIRRO": "FLAMENGO",
                "CEP": "22220030",
                "CIDADE": "RIO DE JANEIRO",
                "ESTADO": "RJ"
            },
            {
                "LOGRADOURO": "R BENTO JOSE RIBEIRO",
                "NUMERO": "18",
                "COMPLEMENTO": "AND 3",
                "BAIRRO": "CENTRO",
                "CEP": "28905090",
                "CIDADE": "CABO FRIO",
                "ESTADO": "RJ"
            },
            {
                "LOGRADOURO": "R PEDRO VALENTIM",
                "NUMERO": "13",
                "COMPLEMENTO": "CS 01",
                "BAIRRO": "PORTINHO",
                "CEP": "28915426",
                "CIDADE": "CABO FRIO",
                "ESTADO": "RJ"
            }
        ]
    },
    "POSSIVEIS_PARENTES": {
        "CONTATO": [
            {
                "CPF": "7544548783",
                "NOME": "VERA LUCIA FONSECA TEIXEIRA",
                "IDADE": "71 anos",
                "LOCAL": "RIO DE JANEIRO\/RJ",
                "PARENTESCO": "MAE"
            },
            {
                "CPF": "7542687727",
                "NOME": "RODRIGO FONSECA TEIXEIRA",
                "IDADE": "47 anos",
                "LOCAL": "RIO DE JANEIRO\/RJ",
                "PARENTESCO": "IRMAO(A)"
            },
            {
                "CPF": "30070609829",
                "NOME": "RODRIGO VALDEZ DA FONSECA TEIXEIRA",
                "IDADE": "44 anos",
                "LOCAL": "SAO PAULO\/SP",
                "PARENTESCO": "IRMAO(A)"
            },
            {
                "CPF": "7609907510",
                "NOME": "AMANDA FONSECA TEIXEIRA",
                "IDADE": "22 anos",
                "LOCAL": "CATU\/BA",
                "PARENTESCO": "FILHO(A)"
            },
            {
                "CPF": "11105893529",
                "NOME": "LEANDRO FONSECA TEIXEIRA",
                "IDADE": "10 anos",
                "LOCAL": "",
                "PARENTESCO": "FILHO(A)"
            }
        ]
    },
    "POSSIVEIS_CONTATOS": "",
    "REFERENCIA_PROFISSIONAL": {
        "EMPRESA": [
            {
                "RAZAO_SOCIAL": "T   S LOCACAO DE MAO DE OBRA EM GERAL LTDA",
                "CNPJ": "12978986000158",
                "CIDADE": "NITEROI-RJ",
                "PROFISSAO": "252105",
                "DATA_ADMISSAO": "25\/01\/2019",
                "DATA_DEMISSAO": "22\/07\/2026",
                "MOTIVO_DESLIGAMENTO": "",
                "ANO_BASE": "2024"
            },
            {
                "RAZAO_SOCIAL": "INSTITUTO DE DIGNIDADE E DESENVOLVIMENTO SOCIAL",
                "CNPJ": "18273227000176",
                "CIDADE": "BELO HORIZONTE-MG",
                "PROFISSAO": "252105",
                "DATA_ADMISSAO": "01\/07\/2024",
                "DATA_DEMISSAO": "{\/{",
                "MOTIVO_DESLIGAMENTO": "",
                "ANO_BASE": "2024"
            },
            {
                "RAZAO_SOCIAL": "INFOTEC CONSULTORIA E PLANEJAMENTO LTDA",
                "CNPJ": "29884632000147",
                "CIDADE": "RIO DE JANEIRO-RJ",
                "PROFISSAO": "252105",
                "DATA_ADMISSAO": "25\/01\/2017",
                "DATA_DEMISSAO": "",
                "MOTIVO_DESLIGAMENTO": "",
                "ANO_BASE": "2019"
            },
            {
                "RAZAO_SOCIAL": "MUNICIPIO DE SAO PEDRO DA ALDEIA",
                "CNPJ": "28909604000174",
                "CIDADE": "SAO PEDRO DA ALDEIA-RJ",
                "PROFISSAO": "111415",
                "DATA_ADMISSAO": "01\/10\/2014",
                "DATA_DEMISSAO": "01\/07\/2016",
                "MOTIVO_DESLIGAMENTO": "",
                "ANO_BASE": "2016"
            },
            {
                "RAZAO_SOCIAL": "MUNICIPIO DE CABO FRIO",
                "CNPJ": "28549483000105",
                "CIDADE": "CABO FRIO-RJ",
                "PROFISSAO": "411005",
                "DATA_ADMISSAO": "01\/01\/2009",
                "DATA_DEMISSAO": "31\/12\/2012",
                "MOTIVO_DESLIGAMENTO": "",
                "ANO_BASE": "2012"
            }
        ]
    },
    "EMPRESAS_SOCIO": {
        "EMPRESA_SOCIO": {
            "RAZAO_SOCIAL": "E.V.V. DE CAXIAS COMERCIO E REPRESENTACOES LTDA.",
            "CNPJ": "03648733000125",
            "CIDADE": "DUQUE DE CAXIAS-RJ",
            "QUALIFICACAO": "Sócio-Administrador",
            "DATA_ENTRADA": "20000215",
            "VALOR_PARTICIPACAO": ""
        }
    }
}