{
    "CADASTRAIS": {
        "CPF": "24967109845",
        "NOME": "MONICA OLIVEIRA ALPIM",
        "NOME_MAE": "ALENICE OLIVEIRA ALPIM",
        "NASCTO": "27\/06\/1975",
        "IDADE": "50 anos",
        "SEXO": "Feminino",
        "RG": "",
        "ORGAO_EMISSOR": "",
        "UF_EMISSAO": "",
        "TITULO_ELEITOR": "267346560159",
        "NIT": "1245035855",
        "ESCOLARIDADE": "",
        "NACIONALIDADE": "Brasileiro ",
        "CBO": "511215",
        "PROFISSAO": "COBRADOR DE TRANSPORTES COLETIVOS (EXCETO TREM)",
        "SALARIO": " 5.413,00",
        "CLASSE_ECONOMICA": "C",
        "CONSTA_OBITO": ""
    },
    "TELEFONES_FIXO": {
        "TELEFONE": {
            "NUMERO": "1124859202",
            "OPERADORA": "VIVO",
            "DATA_REFERENCIA": "",
            "TIPO_TEL": "FIXO",
            "TEM_ZAP": "",
            "NAO_PERTUBE": "não",
            "IMG": "",
            "PRIORIDADE": "media"
        }
    },
    "TELEFONES_MOVEL": {
        "TELEFONE": [
            {
                "NUMERO": "11949572267",
                "OPERADORA": "TIM CELULAR S.A.",
                "DATA_REFERENCIA": "23\/03\/2018",
                "TIPO_TEL": "MOVEL",
                "TEM_ZAP": "",
                "NAO_PERTUBE": "não",
                "IMG": "",
                "PRIORIDADE": ""
            },
            {
                "NUMERO": "11983850619",
                "OPERADORA": "TIM CELULAR S.A.",
                "DATA_REFERENCIA": "23\/03\/2018",
                "TIPO_TEL": "MOVEL",
                "TEM_ZAP": "",
                "NAO_PERTUBE": "não",
                "IMG": "",
                "PRIORIDADE": ""
            },
            {
                "NUMERO": "11972345351",
                "OPERADORA": "VIVO",
                "DATA_REFERENCIA": "",
                "TIPO_TEL": "MOVEL",
                "TEM_ZAP": "",
                "NAO_PERTUBE": "não",
                "IMG": "",
                "PRIORIDADE": "media"
            }
        ]
    },
    "EMAILS": {
        "EMAIL": [
            "monicaalpim@hotmail.com",
            "monicaoliveiraalpim@gmail.com"
        ]
    },
    "ENDERECOS": {
        "ENDERECO": [
            {
                "LOGRADOURO": "R DIONIZIO DIOGO DE FARIA",
                "NUMERO": "3",
                "COMPLEMENTO": "A",
                "BAIRRO": "PRQ CONTINENTAL I",
                "CEP": "07077140",
                "CIDADE": "GUARULHOS",
                "ESTADO": "SP"
            },
            {
                "LOGRADOURO": "R DIONIZIO DIOGO DE FARIA",
                "NUMERO": "39",
                "COMPLEMENTO": "A",
                "BAIRRO": "PRQ CONTINENTAL I",
                "CEP": "07077140",
                "CIDADE": "GUARULHOS",
                "ESTADO": "SP"
            },
            {
                "LOGRADOURO": "R IBIPITANGA",
                "NUMERO": "16",
                "COMPLEMENTO": "A",
                "BAIRRO": "PRQ CONTINENTAL",
                "CEP": "07085260",
                "CIDADE": "GUARULHOS",
                "ESTADO": "SP"
            },
            {
                "LOGRADOURO": "RUA DIONIZIO DIOGO DE FARIA",
                "NUMERO": "98",
                "COMPLEMENTO": "",
                "BAIRRO": "PARQUE CONTINENTAL I",
                "CEP": "07077140",
                "CIDADE": "GUARULHOS",
                "ESTADO": "SP"
            }
        ]
    },
    "POSSIVEIS_PARENTES": {
        "CONTATO": [
            {
                "CPF": "450443841",
                "NOME": "NORMEIDE OLIVEIRA DE ALPIM",
                "IDADE": "66 anos",
                "LOCAL": "GUARULHOS\/SP",
                "PARENTESCO": "IRMAO(A)"
            },
            {
                "CPF": "49796103826",
                "NOME": "MARIANA OLIVEIRA ALPIM SILVA",
                "IDADE": "25 anos",
                "LOCAL": "GUARULHOS\/SP",
                "PARENTESCO": "FILHO(A)"
            }
        ]
    },
    "POSSIVEIS_CONTATOS": {
        "CONTATO": [
            {
                "NOME": "MONICA DE SOUZA SANTOS",
                "IDADE": "",
                "LOCALIDADE": "SALVADOR\/BA",
                "TP_VINCULO": "E-MAIL",
                "CPF": "1209081580"
            },
            {
                "NOME": "RAILDA NEVES LIMA",
                "IDADE": "",
                "LOCALIDADE": "ESPLANADA\/BA",
                "TP_VINCULO": "E-MAIL",
                "CPF": "45215243549"
            },
            {
                "NOME": "VALDELICE DO NASCIMENTO SOUSA",
                "IDADE": "",
                "LOCALIDADE": "SALVADOR\/BA",
                "TP_VINCULO": "E-MAIL",
                "CPF": "79427618515"
            }
        ]
    },
    "REFERENCIA_PROFISSIONAL": {
        "EMPRESA": [
            {
                "RAZAO_SOCIAL": "SAMBAIBA TRANSPORTES URBANOS LTDA.",
                "CNPJ": "01751967000925",
                "CIDADE": "SAO PAULO-SP",
                "PROFISSAO": "511215",
                "DATA_ADMISSAO": "06\/02\/2018",
                "DATA_DEMISSAO": "{\/{",
                "MOTIVO_DESLIGAMENTO": "",
                "ANO_BASE": "2024"
            },
            {
                "RAZAO_SOCIAL": "GPL MOSTRUARIOS LTDA",
                "CNPJ": "02082988000100",
                "CIDADE": "GUARULHOS-SP",
                "PROFISSAO": "763010",
                "DATA_ADMISSAO": "24\/03\/2014",
                "DATA_DEMISSAO": "",
                "MOTIVO_DESLIGAMENTO": "",
                "ANO_BASE": "2014"
            },
            {
                "RAZAO_SOCIAL": "BDN SERVICOS AUXILIARES DE MANUTENCAO PREDIAL LTDA",
                "CNPJ": "15702520000113",
                "CIDADE": "SAO PAULO-SP",
                "PROFISSAO": "763125",
                "DATA_ADMISSAO": "22\/10\/2012",
                "DATA_DEMISSAO": "0",
                "MOTIVO_DESLIGAMENTO": "",
                "ANO_BASE": "2012"
            }
        ]
    },
    "EMPRESAS_SOCIO": ""
}