{
    "CADASTRAIS": {
        "CPF": "45570868291",
        "NOME": "NORMELINA VIANA COSTA",
        "NOME_MAE": "NORMA VIANA COSTA",
        "NASCTO": "23\/11\/1974",
        "IDADE": "51 anos",
        "SEXO": "Feminino",
        "RG": "",
        "ORGAO_EMISSOR": "",
        "UF_EMISSAO": "",
        "TITULO_ELEITOR": "",
        "NIT": "1297677142",
        "ESCOLARIDADE": "",
        "NACIONALIDADE": "Brasileiro ",
        "CBO": "411005",
        "PROFISSAO": "AUXILIAR DE ESCRITORIO, EM GERAL",
        "SALARIO": " 1.779,00",
        "CLASSE_ECONOMICA": "D",
        "CONSTA_OBITO": ""
    },
    "TELEFONES_FIXO": {
        "TELEFONE": [
            {
                "NUMERO": "9130878374",
                "OPERADORA": "CLARO S.A.",
                "DATA_REFERENCIA": "",
                "TIPO_TEL": "FIXO",
                "TEM_ZAP": "",
                "NAO_PERTUBE": "não",
                "IMG": "",
                "PRIORIDADE": "media"
            },
            {
                "NUMERO": "9132384207",
                "OPERADORA": "TELEMAR\/PA",
                "DATA_REFERENCIA": "",
                "TIPO_TEL": "FIXO",
                "TEM_ZAP": "",
                "NAO_PERTUBE": "não",
                "IMG": "",
                "PRIORIDADE": "media"
            }
        ]
    },
    "TELEFONES_MOVEL": {
        "TELEFONE": [
            {
                "NUMERO": "91992020415",
                "OPERADORA": "VIVO",
                "DATA_REFERENCIA": "",
                "TIPO_TEL": "MOVEL",
                "TEM_ZAP": "",
                "NAO_PERTUBE": "não",
                "IMG": "",
                "PRIORIDADE": "alta"
            },
            {
                "NUMERO": "91991120985",
                "OPERADORA": "VIVO",
                "DATA_REFERENCIA": "",
                "TIPO_TEL": "MOVEL",
                "TEM_ZAP": "",
                "NAO_PERTUBE": "não",
                "IMG": "",
                "PRIORIDADE": "alta"
            },
            {
                "NUMERO": "91981531788",
                "OPERADORA": "TIM CELULAR S.A.",
                "DATA_REFERENCIA": "",
                "TIPO_TEL": "MOVEL",
                "TEM_ZAP": "",
                "NAO_PERTUBE": "não",
                "IMG": "",
                "PRIORIDADE": "alta"
            },
            {
                "NUMERO": "91983042156",
                "OPERADORA": "TIM CELULAR S.A.",
                "DATA_REFERENCIA": "",
                "TIPO_TEL": "MOVEL",
                "TEM_ZAP": "",
                "NAO_PERTUBE": "não",
                "IMG": "",
                "PRIORIDADE": "alta"
            },
            {
                "NUMERO": "91984580210",
                "OPERADORA": "CLARO S.A.",
                "DATA_REFERENCIA": "",
                "TIPO_TEL": "MOVEL",
                "TEM_ZAP": "",
                "NAO_PERTUBE": "não",
                "IMG": "",
                "PRIORIDADE": "alta"
            }
        ]
    },
    "EMAILS": {
        "EMAIL": "mdgvianas@ig.com.br"
    },
    "ENDERECOS": {
        "ENDERECO": [
            {
                "LOGRADOURO": "AV ALM BARROSO",
                "NUMERO": "7",
                "COMPLEMENTO": "CS AL",
                "BAIRRO": "S BRAS",
                "CEP": "66090000",
                "CIDADE": "BELEM",
                "ESTADO": "PA"
            },
            {
                "LOGRADOURO": "R STO ANTONIO",
                "NUMERO": "7",
                "COMPLEMENTO": "CAAL",
                "BAIRRO": "CAMPINA",
                "CEP": "66010095",
                "CIDADE": "BELEM",
                "ESTADO": "PA"
            },
            {
                "LOGRADOURO": "PSG STO ANTONIO",
                "NUMERO": "7",
                "COMPLEMENTO": "C AL",
                "BAIRRO": "SOUZA",
                "CEP": "66613163",
                "CIDADE": "BELEM",
                "ESTADO": "PA"
            },
            {
                "LOGRADOURO": "PSG STO ANTONIO",
                "NUMERO": "8",
                "COMPLEMENTO": "",
                "BAIRRO": "MAGUARI",
                "CEP": "67145080",
                "CIDADE": "ANANINDEUA",
                "ESTADO": "PA"
            },
            {
                "LOGRADOURO": "R DO UTINGA",
                "NUMERO": "118",
                "COMPLEMENTO": "C A",
                "BAIRRO": "CURIO UTINGA",
                "CEP": "66610010",
                "CIDADE": "BELEM",
                "ESTADO": "PA"
            },
            {
                "LOGRADOURO": "PASSAGEM SANTO ANTONIO",
                "NUMERO": "8",
                "COMPLEMENTO": "CA AL",
                "BAIRRO": "SOUZA",
                "CEP": "66613163",
                "CIDADE": "BELEM",
                "ESTADO": "PA"
            },
            {
                "LOGRADOURO": "ALAMEDA MINISTRO COSTA CAVALCANTE",
                "NUMERO": "2",
                "COMPLEMENTO": "C C",
                "BAIRRO": "CASTANHEIRA",
                "CEP": "66645555",
                "CIDADE": "BELEM",
                "ESTADO": "PA"
            },
            {
                "LOGRADOURO": "PASSAGEM SANTO ANTONIO",
                "NUMERO": "8",
                "COMPLEMENTO": "",
                "BAIRRO": "CURIO-UTINGA",
                "CEP": "66610180",
                "CIDADE": "BELEM",
                "ESTADO": "PA"
            }
        ]
    },
    "POSSIVEIS_PARENTES": {
        "CONTATO": [
            {
                "CPF": "15423700272",
                "NOME": "NORMA VIANA COSTA",
                "IDADE": "77 anos",
                "LOCAL": "BELEM\/PA",
                "PARENTESCO": "MAE"
            },
            {
                "CPF": "62899481215",
                "NOME": "MARCELO VIANA COSTA",
                "IDADE": "47 anos",
                "LOCAL": "BELEM\/PA",
                "PARENTESCO": "IRMAO(A)"
            },
            {
                "CPF": "85242926287",
                "NOME": "GABRIEL COSTA DE OLIVEIRA",
                "IDADE": "27 anos",
                "LOCAL": "BELEM\/PA",
                "PARENTESCO": "FILHO(A)"
            }
        ]
    },
    "POSSIVEIS_CONTATOS": {
        "CONTATO": {
            "NOME": "MARCELO VIANA COSTA",
            "IDADE": "",
            "LOCALIDADE": "BELEM\/PA",
            "TP_VINCULO": "E-MAIL",
            "CPF": "62899481215"
        }
    },
    "REFERENCIA_PROFISSIONAL": {
        "EMPRESA": {
            "RAZAO_SOCIAL": "ASSOCIACAO CULTURAL E EDUCACIONAL DO PARA",
            "CNPJ": "15254949000195",
            "CIDADE": "BELEM-PA",
            "PROFISSAO": "411005",
            "DATA_ADMISSAO": "11\/02\/2008",
            "DATA_DEMISSAO": "{\/{",
            "MOTIVO_DESLIGAMENTO": "",
            "ANO_BASE": "2024"
        }
    },
    "EMPRESAS_SOCIO": ""
}